barbell2light/__init__.py
barbell2light/utils.py
barbell2light/castorclient/__init__.py
barbell2light/castorclient/castorclient.py
barbell2light/castorexportclient/__init__.py
barbell2light/castorexportclient/castorexportclient.py
barbell2light/dicom/__init__.py
barbell2light/dicom/dcm2masks.py
barbell2light/dicom/dcm2nifti.py
barbell2light/dicom/dcm2numpy.py
barbell2light/dicom/dcm2png.py
barbell2light/dicom/dicomexplorer.py
barbell2light/dicom/nifti2masks.py
barbell2light/dicom/tag2dcm.py
barbell2light/dicom/tag2nifti.py
barbell2light/dicom/tag2numpy.py
barbell2light-1.14.0.dist-info/LICENSE
barbell2light-1.14.0.dist-info/METADATA
barbell2light-1.14.0.dist-info/WHEEL
barbell2light-1.14.0.dist-info/top_level.txt
barbell2light-1.14.0.dist-info/RECORD
