Metadata-Version: 2.1
Name: barbell2light
Version: 1.14.0
Summary: Python Boilerplate contains all the boilerplate you need to create a Python package.
Home-page: https://github.com/rbrecheisen/barbell2light
Author: Ralph Brecheisen
Author-email: ralph.brecheisen@gmail.com
License: MIT license
Keywords: barbell2light
Platform: UNKNOWN
Classifier: Development Status :: 2 - Pre-Alpha
Classifier: Intended Audience :: Developers
Classifier: License :: OSI Approved :: MIT License
Classifier: Natural Language :: English
Classifier: Programming Language :: Python :: 3
Classifier: Programming Language :: Python :: 3.5
Classifier: Programming Language :: Python :: 3.6
Classifier: Programming Language :: Python :: 3.7
Classifier: Programming Language :: Python :: 3.8
Requires-Python: >=3.5
License-File: LICENSE
Requires-Dist: oauthlib
Requires-Dist: requests-oauthlib
Requires-Dist: pydicom
Requires-Dist: cmd2
Requires-Dist: pandas
Requires-Dist: numpy
Requires-Dist: matplotlib
Requires-Dist: python-gdcm
Requires-Dist: pylibjpeg
